echoroboticsapi/__init__.py
echoroboticsapi/api.py
echoroboticsapi/models.py
echoroboticsapi/smart_fetch.py
echoroboticsapi/smart_mode.py
pyechorobotics-1.1.0.dist-info/licenses/LICENSE.md
pyechorobotics-1.1.0.dist-info/METADATA
pyechorobotics-1.1.0.dist-info/WHEEL
pyechorobotics-1.1.0.dist-info/top_level.txt
pyechorobotics-1.1.0.dist-info/RECORD
