Metadata-Version: 2.4
Name: pyechorobotics
Version: 1.1.0
Summary: Access API for echorobotics robot lawn mowers
Author-email: functionpointer <suspendfunction@gmail.com>
License: GNU General Public License v3 or later (GPLv3+)
Project-URL: homepage, https://github.com/functionpointer/pyechorobotics
Classifier: Programming Language :: Python :: 3.11
Classifier: License :: OSI Approved :: GNU General Public License v3 or later (GPLv3+)
Requires-Python: >=3.11
License-File: LICENSE.md
Requires-Dist: aiohttp
Requires-Dist: yarl
Requires-Dist: pydantic<3.0.0,>=2.0.0
Requires-Dist: python-dateutil
Dynamic: license-file
